openwebui_chat_client/__init__.py
openwebui_chat_client/async_openwebui_client.py
openwebui_chat_client/openwebui_chat_client.py
openwebui_chat_client/core/__init__.py
openwebui_chat_client/core/async_base_client.py
openwebui_chat_client/core/base_client.py
openwebui_chat_client/modules/__init__.py
openwebui_chat_client/modules/async_chat_manager.py
openwebui_chat_client/modules/async_file_manager.py
openwebui_chat_client/modules/async_knowledge_base_manager.py
openwebui_chat_client/modules/async_model_manager.py
openwebui_chat_client/modules/async_notes_manager.py
openwebui_chat_client/modules/async_prompts_manager.py
openwebui_chat_client/modules/async_user_manager.py
openwebui_chat_client/modules/chat_manager.py
openwebui_chat_client/modules/file_manager.py
openwebui_chat_client/modules/knowledge_base_manager.py
openwebui_chat_client/modules/model_manager.py
openwebui_chat_client/modules/notes_manager.py
openwebui_chat_client/modules/prompts_manager.py
openwebui_chat_client/modules/user_manager.py
openwebui_chat_client-0.1.24.dist-info/licenses/LICENSE
openwebui_chat_client-0.1.24.dist-info/METADATA
openwebui_chat_client-0.1.24.dist-info/WHEEL
openwebui_chat_client-0.1.24.dist-info/top_level.txt
openwebui_chat_client-0.1.24.dist-info/RECORD
