Metadata-Version: 2.4
Name: openwebui-chat-client
Version: 0.1.24
Summary: A powerful and intelligent Python client for the Open WebUI API.
Author-email: fujie <fj1945@live.cn>
License: GPL-3.0-only
Project-URL: Homepage, https://github.com/Fu-Jie/openwebui-chat-client
Project-URL: Bug Tracker, https://github.com/Fu-Jie/openwebui-chat-client/issues
Project-URL: Documentation, https://github.com/Fu-Jie/openwebui-chat-client#readme
Classifier: Programming Language :: Python :: 3
Classifier: Programming Language :: Python :: 3.8
Classifier: Programming Language :: Python :: 3.9
Classifier: Programming Language :: Python :: 3.10
Classifier: Programming Language :: Python :: 3.11
Classifier: Programming Language :: Python :: 3.12
Classifier: Programming Language :: Python :: 3.13
Classifier: License :: OSI Approved :: GNU General Public License v3 (GPLv3)
Classifier: Operating System :: OS Independent
Classifier: Intended Audience :: Developers
Classifier: Topic :: Software Development :: Libraries :: Python Modules
Classifier: Topic :: Scientific/Engineering :: Artificial Intelligence
Requires-Python: >=3.8
License-File: LICENSE
Requires-Dist: requests
Requires-Dist: python-dotenv
Requires-Dist: httpx
Provides-Extra: test
Requires-Dist: responses; extra == "test"
Dynamic: license-file
